<?xml version="1.0" encoding="windows-1251" ?>
<DB>
<R><Q>Звезда песенного жанра, делающая бизнес на рекламе презервативов?</Q><A>салтыкова</A></R>
<R><Q>Звезда северного полушария, в 23.55 раза ярче Солнца?</Q><A>сириус</A></R>
<R><Q>Звезда песенного жанра, делающая бизнес на рекламе презервативов?</Q><A>салтыкова</A></R>
<R><Q>Звезда эстрады, основная популярность к которой пришла после дурацкой рекламы "Дирола"?</Q><A>орбакайте</A></R>
<R><Q>Звездная роль А. Кузнецова принесла ему много?</Q><A>славы</A></R>
<R><Q>Звездное скопление?</Q><A>галактика</A></R>
<R><Q>Звездоцвет (ботан.)?</Q><A>астра</A></R>
<R><Q>Зверек, ведущий полуводный образ жизни, что, однако, не идет во вред его ценному меху?</Q><A>нутрия</A></R>
<R><Q>Звон поочередно в колокола, начиная с самого большого колокола и кончая наименьшим?</Q><A>перезвон</A></R>
<R><Q>Звук боли?</Q><A>крик</A></R>
<R><Q>Здание для обслуживания и ремонта самолётов?</Q><A>ангар</A></R>
<R><Q>Здание конгресса США, "тезка" одного из семи холмов, на которых возник Рим?</Q><A>капитолий</A></R>
<R><Q>Здание в монастыре, в которое монашествующие собираются для принятия пищи?</Q><A>трапезная</A></R>
<R><Q>Здание конгресса США, "тезка" одного из семи холмов, на которых возник Рим?</Q><A>капитолий</A></R>
<R><Q>Зейнаб, Джамиля, Гюзель... и последняя... ?</Q><A>гюльчатай</A></R>
<R><Q>Зелёный, очень крепкий алкогольный напиток, полынная настойка?</Q><A>абсент</A></R>
<R><Q>Зеленый огонек означает, что ... свободно?</Q><A>такси</A></R>
<R><Q>Зеленый огонек?</Q><A>такси</A></R>
<R><Q>Земельная единица?</Q><A>гектар</A></R>
<R><Q>Земельное владение (истор.)?</Q><A>поместье</A></R>
<R><Q>Земля по отношению к морю?</Q><A>твердь</A></R>
<R><Q>Земноводное животное или растение?</Q><A>амфибия</A></R>
<R><Q>Зеркало, "размножающее" смотрящего в него нарцисса?</Q><A>трельяж</A></R>
<R><Q>Зерновая культура?</Q><A>просо</A></R>
<R><Q>Зима, весна, лето, осень - общее?</Q><A>сезон</A></R>
<R><Q>Зимние белые мухи?</Q><A>снег</A></R>
<R><Q>Зимний катаклизм?</Q><A>град</A></R>
<R><Q>Зимний месяц?</Q><A>февраль</A></R>
<R><Q>Зимний месяц?</Q><A>январь</A></R>
<R><Q>Зимний церковный праздник?</Q><A>крещение</A></R>
<R><Q>Злак?</Q><A>бамбук</A></R>
<R><Q>Злаковое соцветие?</Q><A>колос</A></R>
<R><Q>Злая, сварливая женщина?</Q><A>мегера</A></R>
<R><Q>Злейший враг палочек Коха (специальность врача)?</Q><A>фтизиатр</A></R>
<R><Q>Злоба, язвительность, коварство (одним словом)?</Q><A>ехидство</A></R>
<R><Q>Зловредная африканская муха-кровопийца?</Q><A>цэцэ</A></R>
<R><Q>Злоупротребляющая перекисью водорода?</Q><A>блондинка</A></R>
<R><Q>Змея с капюшоном?</Q><A>кобра</A></R>
<R><Q>Змея, одна из самых крупных (до 10 метров)?</Q><A>питон</A></R>
<R><Q>Знаете ли вы что "косой ..." в шахматной нотации означает "мат"?</Q><A>крест</A></R>
<R><Q>Знаете ли вы кто автор рассказов про Данилу-мастера и Хозяйку Медной Горы?</Q><A>бажов</A></R>
<R><Q>Знак Зодиака?</Q><A>рыбы</A></R>
<R><Q>Знак переноса и короткая соединительная черточка в письме?</Q><A>дефис</A></R>
<R><Q>Знак препинания.</Q><A>запятая</A></R>
<R><Q>Знак препинания?</Q><A>тире</A></R>
<R><Q>Знак царской власти?</Q><A>венец</A></R>
<R><Q>Знак власти, почетного положения?</Q><A>жезл</A></R>
<R><Q>Знак интегрирования и результат этой операции (мат.)?</Q><A>интеграл</A></R>
<R><Q>Знак повышения на полтона в нотном письме?</Q><A>диез</A></R>
<R><Q>Знак понижения на полтона в нотном письме?</Q><A>бемоль</A></R>
<R><Q>Знакомство, используемое в корыстных целях (разг.)?</Q><A>блат</A></R>
</DB>