<?xml version="1.0" encoding="windows-1251" ?>
<DB>
<R><Q>Артист оперетты и киноактер, народный артист СССР (Украина)?</Q><A>водяной</A></R>
<R><Q>Архидискодоны это предки ... ?</Q><A>мамонтов</A></R>
<R><Q>Архипелаг, о котором написал Солженицын?</Q><A>гулаг</A></R>
<R><Q>Архитектор построивший Большой Кремлевский дворец?</Q><A>тон</A></R>
<R><Q>Архитектор, автор проекта здания смольного института?</Q><A>кваренги</A></R>
<R><Q>Архитектурное сооружение, строящееся обычно в честь победы?</Q><A>арка</A></R>
<R><Q>Архитектурный стержень колонны?</Q><A>фуст</A></R>
<R><Q>Архитектурный стиль, который современники называли "варварским"?</Q><A>готика</A></R>
<R><Q>Архитектурный стиль?</Q><A>барокко</A></R>
<R><Q>Атака насекомого?</Q><A>укус</A></R>
<R><Q>Атрибут бога ветра в Древней Греции - это ... ?</Q><A>арфа</A></R>
<R><Q>Афоризм: "Каждый человек стоит столько, сколько он сделал, минус :"?</Q><A>тщеславие</A></R>
<R><Q>Африканская обезьяна?</Q><A>макака</A></R>
<R><Q>Аэропорт Грозного?</Q><A>ханталы</A></R>
<R><Q>Аэропорт в Мюнхене носит имя Франц Йозефа ... ?</Q><A>штрауса</A></R>
<R><Q>Бoльшaя шашлычнaя для изгoлoдавшегoся волкa?</Q><A>кошара</A></R>
<R><Q>Бpодяга местного сообщения?</Q><A>бмс</A></R>
<R><Q>БОЙЛЕР ?</Q><A>котел</A></R>
<R><Q>Бабушкин стиль с точки зрения внука?</Q><A>ретро</A></R>
<R><Q>Бабушкино хранилище?</Q><A>сундук</A></R>
<R><Q>Бал, гулянье, участники которого надевают маски, характерные костюмы?</Q><A>маскарад</A></R>
<R><Q>Балет А.Хачатуряна?</Q><A>спартак</A></R>
<R><Q>Бальный танец?</Q><A>мазурка</A></R>
<R><Q>Бальный танец?</Q><A>танго</A></R>
<R><Q>Бамбуковый медведь?</Q><A>панда</A></R>
<R><Q>Бандит, участник преступной группировки (амер.)?</Q><A>гангстер</A></R>
<R><Q>Бандитское приглашение?</Q><A>сговор</A></R>
<R><Q>Бани, ставшие известной московской достопримечательностью?</Q><A>сандуны</A></R>
<R><Q>Бани, ставшие известной московской достопримечательностью?</Q><A>сандуны</A></R>
<R><Q>Банковская операция?</Q><A>инкассо</A></R>
<R><Q>Басня И.Крылова?</Q><A>лиса</A></R>
<R><Q>Басня Крылова?</Q><A>мешок</A></R>
<R><Q>Басня Крылова?</Q><A>свинья</A></R>
<R><Q>Башмаки из дерева?</Q><A>сабо</A></R>
<R><Q>Беглые набрски наполях рукописей?</Q><A>грифонаж</A></R>
<R><Q>Без ..., не вытащить и рыбку из пруда?</Q><A>труда</A></R>
<R><Q>Без неё на свадьбе скучно?</Q><A>драка</A></R>
<R><Q>Без этого документа вас не примут в поликлинике?</Q><A>полис</A></R>
<R><Q>Безапелляционная истина?</Q><A>догма</A></R>
<R><Q>Беззаботно-радостное настроение?</Q><A>веселье</A></R>
<R><Q>Безлесная равнина?</Q><A>степь</A></R>
<R><Q>Безопасный судовой ход, обозначенный бакенами, створными знаками и пр?</Q><A>фарватер</A></R>
<R><Q>Безотчетное побуждение к чему-либо?</Q><A>инстинкт</A></R>
<R><Q>Белеющий в тумане, одинокий?</Q><A>парус</A></R>
<R><Q>Бело-синий русский народный промысел?</Q><A>гжель</A></R>
<R><Q>Белое марочное вино ?</Q><A>алиготе</A></R>
<R><Q>Белый хлеб продолговатой формы?</Q><A>батон</A></R>
<R><Q>Береговая воинская часть флота для приема и размещения прибывающего пополнения?</Q><A>экипаж</A></R>
<R><Q>Берестяной короб, лучшая из тар под мед и ягоды?</Q><A>туес</A></R>
<R><Q>Беседа журналиста с одним или несколькими лицами по актуальным вопросам?</Q><A>интервью</A></R>
<R><Q>Бесенок из сказки Пушкина, разговаривая с Балдой, ... ?</Q><A>замяукал</A></R>
</DB>