<?xml version="1.0" encoding="windows-1251" ?><DB><R><Q>Приспособление для еды?</Q><A>ложка</A></R><R><Q>Приспособление для зажима обрабатываемого предмета?</Q><A>тиски</A></R><R><Q>Приспособление для ловли бабочек?</Q><A>сачок</A></R><R><Q>Приспособление для ловли рыбы?</Q><A>удочка</A></R><R><Q>Приспособление для перемешивания топлива в печи (толстый железный прут)?</Q><A>кочерга</A></R><R><Q>Приспособление для плавания?</Q><A>акваланг</A></R><R><Q>Приспособление к условиям существования?</Q><A>адаптация</A></R><R><Q>Приспособление для ручного прядения нити?</Q><A>веретено</A></R><R><Q>Пристенный очаг с нависающим дымоходом у народов Севера, Поволжья, Кавказа?</Q><A>чувал</A></R><R><Q>Приток Днепра?</Q><A>друть</A></R><R><Q>Приток Камы?</Q><A>вятка</A></R><R><Q>Приток реки Обь, на берегу которой находится город Омск?</Q><A>иртыш</A></R><R><Q>Притон, место разврата, сбора преступников, наркоманов и пр?</Q><A>вертеп</A></R><R><Q>Причальный канат для речного судна, лодки?</Q><A>чалка</A></R><R><Q>Пришедше из Японии искусство составления букетов и композиций из растений?</Q><A>икебана</A></R><R><Q>Про какого поэта Бунин говорил: "У него вместо мозгов хризантема"?</Q><A>бальмонт</A></R><R><Q>Пробившийся корень?</Q><A>росток</A></R><R><Q>Пробитая рекой расщелина в скалах, глубокая узкая долина с обрывистыми склонами?</Q><A>каньон</A></R><R><Q>Проверочный опрос, экзамен?</Q><A>испытание</A></R><R><Q>Провод до розетки?</Q><A>шнур</A></R><R><Q>Программа, выполняющая служебные или вспомогательные функции (комп. жарг.)?</Q><A>утилита</A></R><R><Q>Программный номер в цирке?</Q><A>иллюзия</A></R><R><Q>Продавец старинных книг, картин и т.п?</Q><A>антиквар</A></R><R><Q>Продажность, взяточничество должностных лиц и политиков?</Q><A>коррупция</A></R><R><Q>Продолжения какого мероприятия требовал И.В. Бунша?</Q><A>банкета</A></R><R><Q>Продолжите фразу: "Хочешь обнять весь мир, купи ..."?</Q><A>глобус</A></R><R><Q>Продукт вдохновенного труда всех кулибиных?</Q><A>самоделка</A></R><R><Q>Продукт жизнедеятельности?</Q><A>пот</A></R><R><Q>Продукт застойной воды?</Q><A>тина</A></R><R><Q>Продукт изнурительной работы?</Q><A>пот</A></R><R><Q>Продукт обжига известняка?</Q><A>известь</A></R><R><Q>Продукт питания из теста и мяса?</Q><A>пельмени</A></R><R><Q>Продукт питания?</Q><A>ростбиф</A></R><R><Q>Продукт размола зерна?</Q><A>мука</A></R><R><Q>Продукт сухой перегонки каменного угля?</Q><A>кокс</A></R><R><Q>Продукт, из которого человек получает те же вещества, которые выделяются при оргазме?</Q><A>шоколад</A></R><R><Q>Продукт, из которого человек получает те же вещества, которые выделяются при оргазме?</Q><A>шоколад</A></R><R><Q>Продукт сухой перегонки древесины ?</Q><A>деготь</A></R><R><Q>Продюсер, основное занятие которого - дрессировка музыкальных мальчиков?</Q><A>алибасов</A></R><R><Q>Проезжая дорога, выложенная булыжником?</Q><A>мостовая</A></R><R><Q>Прозвище героя Вахтанга Кикабидзе в одноименном фильме Г.Данелии?</Q><A>мимино</A></R><R><Q>Прозвище падающего на стол после первого стакана водки?</Q><A>слабак</A></R><R><Q>Прозвище североамериканцев в Лат. Америке?</Q><A>гринго</A></R><R><Q>Прозрачная бесцветная жидкость?</Q><A>вода</A></R><R><Q>Прозрачная бесцветная жидкость?</Q><A>уксус</A></R><R><Q>Произведение Франсуа Вийона, написанное в ожидании смертной казни?</Q><A>эпитафия</A></R><R><Q>Произведение всех чисел от единицы до "Эн" называется ... ?</Q><A>факториал</A></R><R><Q>Произведение живописи?</Q><A>картина</A></R><R><Q>Произведение профессора Преображенского ("Собачье сердце" М. Булгакова)?</Q><A>шариков</A></R><R><Q>Производная работы по времени?</Q><A>мощность</A></R><R><Q>Произвол, вседозволенность(жарг.)?</Q><A>беспредел</A></R><R><Q>Произношение, выговор?</Q><A>прононс</A></R><R><Q>Произношение, манера выговаривать слова?</Q><A>дикция</A></R><R><Q>Происшествие или приключение - обычно смешное, затруднительное, необычайное?</Q><A>казус</A></R><R><Q>Происшествие, когда любовник, сидящий в шкафу вынужден орать: "Выносите мебель!"?</Q><A>пожар</A></R><R><Q>Промежуток вмерени, равный 1/1440 суток?</Q><A>минута</A></R><R><Q>Промежуток вмерени, равный 3600 секундам?</Q><A>час</A></R><R><Q>Промежуток времени, о котором не стоит думать свысока?</Q><A>секунда</A></R><R><Q>Промежуток времени, равный 3600 секундам?</Q><A>час</A></R><R><Q>Промысловая рыба, крупный лещ?</Q><A>чебак</A></R><R><Q>Промысловая рыба, обитающая в реках и озерах Сибири?</Q><A>ленок</A></R><R><Q>Промысловое морское ракообразное?</Q><A>криль</A></R><R><Q>Промысловое название некоторых членистоногих видов морского рака?</Q><A>криль</A></R><R><Q>Прорванное или проломанное отверстие?</Q><A>дыра</A></R><R><Q>Пророк зеленого знамени?</Q><A>мухаммед</A></R><R><Q>Просачивание растворителя сквозь перегородку?</Q><A>осмос</A></R><R><Q>Прославленный русский адмирал, не знавший поражений в морских битвах(фамилия)?</Q><A>ушаков</A></R><R><Q>Прославленный хоккеист, неоднократный чемпион мира, Олимпийских игр?</Q><A>третьяк</A></R><R><Q>Простейшее грузоподъемное устройство?</Q><A>ворот</A></R><R><Q>Простейшее низшее многоклеточное?</Q><A>гидра</A></R><R><Q>Простейшие рычажные или пружинные весы?</Q><A>безмен</A></R><R><Q>Простые и сложные элементы - классы органич. соединений (хим.)?</Q><A>эфир</A></R><R><Q>Просьба, рассчитанная не на любезность, а на сострадание?</Q><A>мольба</A></R><R><Q>Противное сумчатое животное?</Q><A>ехидна</A></R><R><Q>Противогазное устройство в автомобиле?</Q><A>тормоз</A></R><R><Q>Противопоставление своих взглядов, политики другой политике, взглядам?</Q><A>оппозиция</A></R><R><Q>Протокол работы программы?</Q><A>лог</A></R><R><Q>Прототип какого сказочного героя вызывает слезы?</Q><A>чипполино</A></R><R><Q>Профессиональный наёмный убийца?</Q><A>киллер</A></R><R><Q>Профессия Квазимодо?</Q><A>звонарь</A></R><R><Q>Профессия врача?</Q><A>ортопед</A></R><R><Q>Профессия рабочего?</Q><A>слесарь</A></R><R><Q>Профессия ученого, изучающего птиц?</Q><A>орнитолог</A></R><R><Q>Профессорская трибуна?</Q><A>кафедра</A></R><R><Q>Прохладительный напиток?</Q><A>лимонад</A></R><R><Q>Прохладительный напиток?</Q><A>ситро</A></R><R><Q>Прохладительный сладкий напиток из разбавленного водой сока ягод или плодов?</Q><A>морс</A></R><R><Q>Процесс переработки нефти с целью получения моторных топлив?</Q><A>крекинг</A></R><R><Q>Процесс приобретения знаний?</Q><A>учение</A></R><R><Q>Процесс сооружения горной выработки для добычи полезных ископаемых и т.д.?</Q><A>бурение</A></R><R><Q>Прочная защитная облицовка на военных судах, танках, машинах, оборонительных сооружениях?</Q><A>броня</A></R><R><Q>Прыгун в воду, получивший 10,0 от всех судей?</Q><A>финнеран</A></R><R><Q>Прыгун в высоту, первым преодолевший высоту в семь футов?</Q><A>брумель</A></R><R><Q>Прыжок с переворотом тела в воздухе, который циркачи назвали "мортале" - смертельный?</Q><A>сальто</A></R><R><Q>Прямая, проходящая через точку кривой и перпендикулярная касательной?</Q><A>нормаль</A></R><R><Q>Прямоугольный двор, окруженный колоннадой?</Q><A>перистиль</A></R><R><Q>Пряность; сушеная кора ветвей коричных деревьев?</Q><A>корица</A></R><R><Q>Пряность?</Q><A>горчица</A></R><R><Q>Пряность?</Q><A>корица</A></R><R><Q>Пряность?</Q><A>перец</A></R></DB>