<?xml version="1.0" encoding="windows-1251" ?><DB><R><Q>Столица государства Кирибати?</Q><A>байрики</A></R><R><Q>Столица государства на северо-западе Руси?</Q><A>новгород</A></R><R><Q>Столица украинских шахтеров?</Q><A>донецк</A></R><R><Q>Столица штата Вайоминг?</Q><A>шайенн</A></R><R><Q>Столица этого государства - самая северная в мире - ... ?</Q><A>рейкьявик</A></R><R><Q>Столицей какой республики является Тегусигальпа?</Q><A>гондурас</A></R><R><Q>Столовый прибор, который по распространенности занимает второе место в мире?</Q><A>палочки</A></R><R><Q>Столовый прибор?</Q><A>секира</A></R><R><Q>Столовый прибор, который по распространенности занимает второе место в мире?</Q><A>палочки</A></R><R><Q>Столярный инструмент, однажды пропитый лешим?</Q><A>долото</A></R><R><Q>Столярный разметочный инструмент?</Q><A>угольник</A></R><R><Q>Стопкран у корабля?</Q><A>якорь</A></R><R><Q>Сторона монеты, обратная гербу?</Q><A>решка</A></R><R><Q>Сторона треугольника, уже "обзаведшегося" гипотенузой?</Q><A>катет</A></R><R><Q>Сторонник одного из религиозных течений во Франции в 16-18 вв?</Q><A>гугенот</A></R><R><Q>Страж Турецкого паши?</Q><A>делибаш</A></R><R><Q>Страна в которой находится самая низкая точка Южной Америки?</Q><A>аргентина</A></R><R><Q>Страна, в которой даже дожди и те - косые?</Q><A>россия</A></R><R><Q>Страна, в которой жил литературный персонаж Рикки-Тикки-Тави?</Q><A>индия</A></R><R><Q>Страна, где в 6 веке появились первые ветряные мельницы?</Q><A>персия</A></R><R><Q>Страна, где впервые появилось звание "офицер"?</Q><A>франция</A></R><R><Q>Страна, где впервые установлена всеобщая воинская повинность?</Q><A>франция</A></R><R><Q>Страна, где вращается самое большое количество 100-долларовых купюр?</Q><A>россия</A></R><R><Q>Страна, где зародилась игра в бадминтон?</Q><A>англия</A></R><R><Q>Страна, где находится святая гора Афон?</Q><A>греция</A></R><R><Q>Страна, где обитает единственная в мире ядовитая ящерица?</Q><A>мексика</A></R><R><Q>Страна, где чаем отгоняли сон уже пять тысяч лет назад, считается родиной чая - это ... ?</Q><A>китай</A></R><R><Q>Страна, подарившая свое название породе самых хищных и злобных кошек?</Q><A>сиам</A></R><R><Q>Страна, где платят кипами, а сдачу получают атами?</Q><A>лаос</A></R><R><Q>Страна, из которой происходит автор романа "Сто лет одиночества"?</Q><A>колумбия</A></R><R><Q>Страна благотворного неравенства"?</Q><A>америка</A></R><R><Q>Страна с наибольшим количеством людей, говорящих по-английски?</Q><A>китай</A></R><R><Q>Страстный болельщик?</Q><A>фанат</A></R><R><Q>Страстный любитель музыки?</Q><A>меломан</A></R><R><Q>Страсть к спичечным коробкам - это ... ?</Q><A>филумения</A></R><R><Q>Страховое свидетельство?</Q><A>полис</A></R><R><Q>Стремительный натиск, сопровождаемый традиционным "Ура"?</Q><A>атака</A></R><R><Q>Стрессовый гормон?</Q><A>адреналин</A></R><R><Q>Стрижка прямоугольной формы?</Q><A>каре</A></R><R><Q>Строгая мораль и чистота нравов?</Q><A>пуризм</A></R><R><Q>Строение чего-либо, соответствующее определенной ступени развития?</Q><A>формация</A></R><R><Q>Строжка, циклевание, натирка, лакирование - способы отделки ... ?</Q><A>паркета</A></R><R><Q>Строй боевых самолетов?</Q><A>пеленг</A></R><R><Q>Стройматериал?</Q><A>доломит</A></R><R><Q>Стройматериал?</Q><A>кирпич</A></R><R><Q>Стройматериал?</Q><A>цемент</A></R><R><Q>Строптивец, укрощенный Орнеллой Мути в популярном фильме?</Q><A>челентано</A></R><R><Q>Строфа из 4 стихов?</Q><A>терцет</A></R><R><Q>Струнный музыкальный инструмент.</Q><A>мандолина</A></R><R><Q>Струнный музыкальный инструмент?</Q><A>арфа</A></R><R><Q>Струнный музыкальный инструмент?</Q><A>банджо</A></R><R><Q>Струнный музыкальный инструмент?</Q><A>гитара</A></R><R><Q>Струнный музыкальный инструмент?</Q><A>гусли</A></R><R><Q>Струнный музыкальный инструмент?</Q><A>рояль</A></R><R><Q>Струнный музыкальный инструмент?</Q><A>скрипка</A></R><R><Q>Студентам горного института, наверное, нравится этот голливудский блокбастер?</Q><A>скалолаз</A></R><R><Q>Субстанция в море, из которой по преданию вышла богиня Венера?</Q><A>пена</A></R><R><Q>Суверенный "карлик" в Европе?</Q><A>монако</A></R><R><Q>Судимый за приземление на Красной площади немецкий пилот?</Q><A>руст</A></R><R><Q>Судно, буксирующее плоты при сплаве леса?</Q><A>лесовоз</A></R><R><Q>Судовая лестница?</Q><A>трап</A></R><R><Q>Судя по названию, этот костюм предназначен только для курящих?</Q><A>смокинг</A></R><R><Q>Судя по истории нашего государства, девиз россиян: "Через тернии - к ...!"?</Q><A>терниям</A></R><R><Q>Суковатое затонувшее дерево?</Q><A>коряга</A></R><R><Q>Сульфат железа, меди или цинка - это ... ?</Q><A>купорос</A></R><R><Q>Сумка для ношения продуктов?</Q><A>сетка</A></R><R><Q>Сумма сведений о преступнике?</Q><A>досье</A></R><R><Q>Сумма денег, примерно в два раза меньшая, чем та, чего вы действительно стоите?</Q><A>зарплата</A></R><R><Q>Сумчатое животное, обитающее в Северной Америке?</Q><A>опоссум</A></R><R><Q>Супругой Геракла была?</Q><A>геба</A></R><R><Q>Сустав, соединяющий бедренную и берцовую кости; место сгиба на ноге?</Q><A>коленка</A></R><R><Q>Суточный рацион?</Q><A>диета</A></R><R><Q>Сухая долина?</Q><A>вади</A></R><R><Q>Суша, на которой корабли ведут здоровый образ жизни?</Q><A>стапель</A></R><R><Q>Сушка продуктов на открытом воздухе на ветру?</Q><A>вяление</A></R><R><Q>Существо, которое принято звать джус, кент, крендель или шорик. (молодежный сленг)?</Q><A>приятель</A></R><R><Q>Существовала пионерская поговорка: "Пионер - всем ребятам ..."?</Q><A>пример</A></R><R><Q>Существует только один заменитель воображения - ... (Берджес)?</Q><A>опыт</A></R><R><Q>Схема какого-нибудь физического объекта или явления?</Q><A>модель</A></R><R><Q>Сценическая площадка?</Q><A>арена</A></R><R><Q>Счастье по Марксу?</Q><A>борьба</A></R><R><Q>Съедобный пластинчатый гриб?</Q><A>груздь</A></R><R><Q>Съестное, рассчитанное на тонкий вкус при толстом кошельке?</Q><A>деликатес</A></R><R><Q>Сын Владимира Мономаха Юрий получил прозвище Долгорукий за посягательство на ... ?</Q><A>киев</A></R><R><Q>Сын Гелиоса, не справившийся с управлением его колесницы?</Q><A>фаэтон</A></R><R><Q>Сын разорившегося купца из комедии А.Н.Островского " Горячее сердце "?</Q><A>вася</A></R><R><Q>Сын сына или дочери?</Q><A>внук</A></R><R><Q>Сын Адама и Евы, убитый из зависти собственным братом Каином?</Q><A>авель</A></R><R><Q>Сыр из овечьего молока или смеси овечьего и козьего?</Q><A>брынза</A></R><R><Q>Сырые дрова легко вспыхнут, если на них высыпать горсть ... ?</Q><A>соли</A></R><R><Q>Сырье для манной каши?</Q><A>пшено</A></R><R><Q>Тopгoвый oбычaй</Q><A>узанс</A></R><R><Q>Та, которую 3евс, обратившись в быка, увез на себе?</Q><A>европа</A></R><R><Q>Таблетки от кашля, от которых можно стать наркоманом?</Q><A>кодеин</A></R><R><Q>Так в Государственной думе РФ называют сельскохозяйственных рабочих?</Q><A>аграрии</A></R><R><Q>Так в Древней Греции назывался сплав золота с серебром?</Q><A>электрон</A></R><R><Q>Так в Древнем Риме называли раба, сопровождавшего ребенка в школу и обратно домой?</Q><A>педагог</A></R><R><Q>Так кричит солдат, когда ему хорошо, а врагу плохо?</Q><A>ура</A></R><R><Q>Так моряк называет запад?</Q><A>вест</A></R><R><Q>Так мы называем день недели, когда Бог сотворил Адама и Еву?</Q><A>пятница</A></R></DB>